fresco_fs.py
fresco_fs-0.1.1.dist-info/DESCRIPTION.rst
fresco_fs-0.1.1.dist-info/METADATA
fresco_fs-0.1.1.dist-info/RECORD
fresco_fs-0.1.1.dist-info/WHEEL
fresco_fs-0.1.1.dist-info/metadata.json
fresco_fs-0.1.1.dist-info/top_level.txt
