Metadata-Version: 2.0
Name: fresco-fs
Version: 0.1.1
Summary: Filesystem resources for fresco
Home-page: https://skot.be/
Author: Oliver Cope
Author-email: oliver@redgecko.org
License: Apache
Platform: UNKNOWN
Requires-Dist: fresco
